{
  "2022-01-16 19-09-00": {
    "planar": {
      "normal": [
        0.16969603058284,
        0.9832445225177111,
        -0.06658427849985567
      ],
      "status": "ok",
      "triplet": [
        "ace",
        "wind",
        "dscovr"
      ],
      "velocity": [
        -541.7999877929688,
        20.799999237060547,
        -75.69999694824219
      ],
      "velocity_sat": "dscovr"
    },
    "spherical": {
      "center": [
        1725.561842158217,
        -7018.328399298032,
        -3291.69501974495
      ],
      "method": "fixed_radius_4sat",
      "normals": {
        "ace": [
          -0.11402840407165703,
          0.8957877474056256,
          0.4296066045381821
        ],
        "dscovr": [
          -0.19142222351185306,
          0.8889355995506875,
          0.41611420571429436
        ],
        "mms1": [
          -0.13997675362768186,
          0.8916914920793129,
          0.43045649187487445
        ],
        "wind": [
          -0.1100508546363317,
          0.8952461807626315,
          0.4317673971292121
        ]
      },
      "r0": 7849.5892342798015,
      "reference_sat": "dscovr",
      "satellites": [
        "ace",
        "wind",
        "dscovr",
        "mms1"
      ],
      "sigma": 61616051.14692136,
      "status": "ok",
      "velocity": [
        -541.7999877929688,
        20.799999237060547,
        -75.69999694824219
      ],
      "velocity_sat": "dscovr"
    }
  },
  "2022-11-24 19-10-00": {
    "planar": {
      "normal": [
        -0.3954599789708755,
        -0.23149983357548073,
        -0.8888302605598437
      ],
      "status": "ok",
      "triplet": [
        "ace",
        "wind",
        "dscovr"
      ],
      "velocity": [
        -314.8999938964844,
        10.699999809265137,
        0.800000011920929
      ],
      "velocity_sat": "dscovr"
    },
    "spherical": {
      "center": [
        165.8857531602306,
        7.8369980776534724,
        -115.22975074079821
      ],
      "method": "fixed_radius_4sat",
      "normals": {
        "ace": [
          0.3826584796941328,
          -0.12195200203892369,
          0.9158057638587308
        ],
        "dscovr": [
          0.5076881740137277,
          -0.16806720523730234,
          0.8449888357193422
        ],
        "mms1": [
          -0.7049561030434895,
          0.017567166028556052,
          0.7090333472125708
        ],
        "wind": [
          0.29427578743151206,
          0.5919944105198094,
          0.7502961940759576
        ]
      },
      "r0": 151.2874621461097,
      "reference_sat": "dscovr",
      "satellites": [
        "ace",
        "wind",
        "dscovr",
        "mms1"
      ],
      "sigma": 22887.896202610576,
      "status": "ok",
      "velocity": [
        -314.8999938964844,
        10.699999809265137,
        0.800000011920929
      ],
      "velocity_sat": "dscovr"
    }
  },
  "2023-02-26 19-23-00": {
    "planar": {
      "normal": [
        -0.6771947409397944,
        -0.007369625525467846,
        -0.7357669274050709
      ],
      "status": "ok",
      "triplet": [
        "ace",
        "wind",
        "dscovr"
      ],
      "velocity": [
        -527.4000244140625,
        59.29999923706055,
        39.79999923706055
      ],
      "velocity_sat": "dscovr"
    },
    "spherical": {
      "center": [
        161.48340270770294,
        -41.86825194743601,
        -2.6456505629382314
      ],
      "method": "fixed_radius_4sat",
      "normals": {
        "ace": [
          0.867190885779569,
          0.4351213212436986,
          -0.24217638906380748
        ],
        "dscovr": [
          0.6478657730366741,
          0.7614944424424812,
          -0.019903624212872277
        ],
        "mms1": [
          -0.9167699404620934,
          0.3817171361104482,
          -0.11757935305472292
        ],
        "wind": [
          0.7676869910444728,
          -0.6382134019597838,
          0.05779565156655819
        ]
      },
      "r0": 94.20234728545776,
      "reference_sat": "ace",
      "satellites": [
        "ace",
        "wind",
        "dscovr",
        "mms1"
      ],
      "sigma": 8874.082234089992,
      "status": "ok",
      "velocity": [
        -527.4000244140625,
        59.29999923706055,
        39.79999923706055
      ],
      "velocity_sat": "dscovr"
    }
  },
  "2023-07-16 19-20-00": {
    "planar": {
      "normal": [
        -0.006699403919243865,
        -0.9573938424285621,
        0.28870772152299734
      ],
      "status": "ok",
      "triplet": [
        "ace",
        "dscovr",
        "themis-b"
      ],
      "velocity": [
        -503.29998779296875,
        5.400000095367432,
        6.400000095367432
      ],
      "velocity_sat": "dscovr"
    },
    "spherical": {
      "satellites": [
        "ace",
        "dscovr",
        "themis-b"
      ],
      "status": "insufficient_satellites"
    }
  },
  "2024-04-29 18-31-00": {
    "planar": {
      "normal": [
        0.11120785297781434,
        0.9937254013126775,
        0.011943208196417672
      ],
      "status": "ok",
      "triplet": [
        "ace",
        "wind",
        "dscovr"
      ],
      "velocity": [
        -473.70001220703125,
        53.099998474121094,
        -12.699999809265137
      ],
      "velocity_sat": "dscovr"
    },
    "spherical": {
      "center": [
        -267124.42210840265,
        -5754793.47980188,
        -972077.2433076331
      ],
      "method": "fixed_radius_4sat",
      "normals": {
        "ace": [
          0.04582433949082313,
          0.984995040398654,
          0.16638780093589745
        ],
        "dscovr": [
          0.04582826175977226,
          0.9849945818130885,
          0.16638943543066856
        ],
        "mms1": [
          0.04572422509804092,
          0.9850007173169935,
          0.1663817361497108
        ],
        "wind": [
          0.16425490221382794,
          0.9717355715380831,
          0.16955915223390608
        ]
      },
      "r0": 5842402.629657139,
      "reference_sat": "mms1",
      "satellites": [
        "ace",
        "wind",
        "dscovr",
        "mms1"
      ],
      "sigma": 34133668487024.652,
      "status": "ok",
      "velocity": [
        -473.70001220703125,
        53.099998474121094,
        -12.699999809265137
      ],
      "velocity_sat": "dscovr"
    }
  },
  "2024-05-10 16-36-00": {
    "planar": {
      "status": "insufficient_satellites"
    },
    "spherical": {
      "satellites": [
        "ace",
        "wind"
      ],
      "status": "insufficient_satellites"
    }
  },
  "2024-06-28 07-00-00": {
    "planar": {
      "normal": [
        0.5910325928529742,
        0.7970296272239531,
        0.12419439404714223
      ],
      "status": "ok",
      "triplet": [
        "ace",
        "wind",
        "mms1"
      ],
      "velocity": [
        -320.1883544921875,
        -40.51483154296875,
        11.546438217163086
      ],
      "velocity_sat": "wind"
    },
    "spherical": {
      "center": [
        -1395.1091404235942,
        8386.06894802065,
        27630.18056772968
      ],
      "method": "fixed_radius_4sat",
      "normals": {
        "ace": [
          0.0682923806850494,
          -0.28708190226448066,
          -0.9554685406294524
        ],
        "mms1": [
          0.0494396684181817,
          -0.29056563015448506,
          -0.9555769638075351
        ],
        "themis-b": [
          0.048104836119678744,
          -0.29185190519388376,
          -0.9552530503361919
        ],
        "wind": [
          0.06914784445825818,
          -0.28781245246864046,
          -0.9551871899322997
        ]
      },
      "r0": 28925.40930854728,
      "reference_sat": "themis-b",
      "satellites": [
        "ace",
        "mms1",
        "themis-b",
        "wind"
      ],
      "sigma": 836679303.6669937,
      "status": "ok",
      "velocity": [
        -320.1883544921875,
        -40.51483154296875,
        11.546438217163086
      ],
      "velocity_sat": "wind"
    }
  },
  "2024-10-06 07-39-00": {
    "planar": {
      "status": "insufficient_satellites"
    },
    "spherical": {
      "satellites": [],
      "status": "insufficient_satellites"
    }
  },
  "2025-06-01 19-19-00": {
    "planar": {
      "normal": [
        -0.26179086881708086,
        -0.15267034607659072,
        0.952972878120281
      ],
      "status": "ok",
      "triplet": [
        "ace",
        "wind",
        "dscovr"
      ],
      "velocity": [
        -465.70001220703125,
        6.400000095367432,
        0.5
      ],
      "velocity_sat": "dscovr"
    },
    "spherical": {
      "satellites": [
        "ace",
        "dscovr",
        "wind"
      ],
      "status": "insufficient_satellites"
    }
  }
}